LICENCE.md
README.md
setup.py
gene_loci_comparison/CustomBiopythonTranslator.py
gene_loci_comparison/Loci.py
gene_loci_comparison/Locus.py
gene_loci_comparison/__init__.py
gene_loci_comparison/utils.py
gene_loci_comparison.egg-info/PKG-INFO
gene_loci_comparison.egg-info/SOURCES.txt
gene_loci_comparison.egg-info/dependency_links.txt
gene_loci_comparison.egg-info/requires.txt
gene_loci_comparison.egg-info/top_level.txt
tests/test_loci.py
tests/test_locus.py