Metadata-Version: 2.1
Name: gene-loci-comparison
Version: 0.0.4
Summary: Create fancy (bokeh) gene locus plots from GenBank files
Home-page: https://github.com/MrTomRod/gene_loci_comparison
Author: Thomas Roder
Author-email: roder.thomas@gmail.com
License: MIT
Classifier: License :: OSI Approved :: MIT License
Classifier: Programming Language :: Python :: 3
Classifier: Programming Language :: Python :: 3.9
Classifier: Programming Language :: Python :: 3.10
License-File: LICENCE.md
Requires-Dist: pandas
Requires-Dist: biopython
Requires-Dist: dna-features-viewer
Requires-Dist: bokeh
